chess/__init__.py
chess/__main__.py
chess/chess.py
chess/cluster.py
chess/defaults.py
chess/distance.py
chess/graph.py
chess/query.py
chess/search.py
CHESS_python_nightly-1.1.0.dist-info/LICENSE.md
CHESS_python_nightly-1.1.0.dist-info/METADATA
CHESS_python_nightly-1.1.0.dist-info/WHEEL
CHESS_python_nightly-1.1.0.dist-info/top_level.txt
CHESS_python_nightly-1.1.0.dist-info/RECORD
