Metadata-Version: 2.1
Name: CHESS-python-nightly
Version: 1.1.0
Summary: Clustered Hierarchical Entropy-Scaling Search
Home-page: https://github.com/nishaq503/CHESS
Author: Najib Ishaq
Author-email: 
License: UNKNOWN
Platform: UNKNOWN
Requires-Python: >=3.6
Requires-Dist: numpy
Requires-Dist: scipy
